vertica_backup/utils.py
vertica_backup/epoch.py
vertica_backup/restore_download.py
vertica_backup/__init__.py
vertica_backup/backup.py
vertica_backup/directory_metadata.py
vertica_backup/object_store/fs.py
vertica_backup/object_store/base.py
vertica_backup/object_store/__init__.py
vertica_backup/object_store/swift.py
vertica_swift_backup-1.1.1.dist-info/METADATA
vertica_swift_backup-1.1.1.dist-info/DESCRIPTION.rst
vertica_swift_backup-1.1.1.dist-info/metadata.json
vertica_swift_backup-1.1.1.dist-info/top_level.txt
vertica_swift_backup-1.1.1.dist-info/RECORD
vertica_swift_backup-1.1.1.dist-info/entry_points.txt
vertica_swift_backup-1.1.1.dist-info/WHEEL
vertica_swift_backup-1.1.1.data/data/share/vertica-swift-backup/examples/backup.yaml-example
vertica_swift_backup-1.1.1.data/data/share/vertica-swift-backup/restore/fabfile.py
vertica_swift_backup-1.1.1.data/data/share/vertica-swift-backup/restore/vertica.py
vertica_swift_backup-1.1.1.data/data/share/vertica-swift-backup/restore/README.md
