Metadata-Version: 2.0
Name: vertica-swift-backup
Version: 1.1.1
Summary: A script to backup/restore Vertica to OpenStack Swift.
Home-page: https://github.com/tkuhlman/vertica-swift-backup
Author: Tim Kuhlman
Author-email: tim@backgroundprocess.com
License: BSD
Keywords: vertica swift openstack cloud backup
Platform: UNKNOWN
Classifier: Development Status :: 5 - Production/Stable
Classifier: License :: OSI Approved :: BSD License
Classifier: Topic :: Database
Classifier: Topic :: System :: Archiving :: Backup
Requires-Dist: setuptools
Requires-Dist: python-swiftclient
Requires-Dist: python-keystoneclient
Requires-Dist: PyYAML
